gaiaclient.py
gaiaclient-1.7.10.dist-info/LICENSE
gaiaclient-1.7.10.dist-info/METADATA
gaiaclient-1.7.10.dist-info/WHEEL
gaiaclient-1.7.10.dist-info/top_level.txt
gaiaclient-1.7.10.dist-info/RECORD
