Metadata-Version: 2.1
Name: gaiaclient
Version: 1.7.10
Summary: Client for JOT Automation gaia machines
Home-page: https://github.com/jotautomation/gaiapythonclient
Author: JOT Automation Ltd.
Author-email: info@jotautomation.com
License: MIT License
Platform: UNKNOWN
Classifier: Programming Language :: Python :: 3
Classifier: License :: OSI Approved :: MIT License
Classifier: Operating System :: OS Independent
Requires-Dist: wheel
Requires-Dist: requests
Requires-Dist: websocket-client
